sofastorage/__init__.py
sofastorage/key.py
sofastorage/sofa.py
sofastorage-0.0.2.dist-info/METADATA
sofastorage-0.0.2.dist-info/WHEEL
sofastorage-0.0.2.dist-info/top_level.txt
sofastorage-0.0.2.dist-info/RECORD
