Metadata-Version: 2.1
Name: sofastorage
Version: 0.0.2
Summary: Easy to use password manager
Home-page: https://github.com/SlumberDemon/SofaStorage
Author: SlumberDemon
Project-URL: Bug Reports, https://github.com/SlumberDemon/SofaStorage/issues
Project-URL: Source, https://github.com/SlumberDemon/SofaStorage
Keywords: storage,password-storage,password-manager,storage-service,web-storage
Classifier: License :: OSI Approved :: MIT License
Classifier: Programming Language :: Python :: 3
Classifier: Programming Language :: Python :: 3.6
Classifier: Programming Language :: Python :: 3.7
Classifier: Programming Language :: Python :: 3.8
Classifier: Programming Language :: Python :: 3.9
Classifier: Programming Language :: Python :: 3.10
Classifier: Programming Language :: Python :: 3 :: Only
Requires-Python: >=3.6, <4
Requires-Dist: deta
Requires-Dist: tabulate
